pulumi_aws_lambdaedge/__init__.py
pulumi_aws_lambdaedge/tests.py
pulumi_aws_lambdaedge-0.1.1.data/data/requirements.txt
pulumi_aws_lambdaedge-0.1.1.dist-info/METADATA
pulumi_aws_lambdaedge-0.1.1.dist-info/WHEEL
pulumi_aws_lambdaedge-0.1.1.dist-info/top_level.txt
pulumi_aws_lambdaedge-0.1.1.dist-info/RECORD
