Metadata-Version: 2.1
Name: pulumi-aws-lambdaedge
Version: 0.1.1
Summary: Pulumi ComponentResource for create Lambda@Edge
Home-page: https://github.com/jetbrains-infra/pulumi-aws-lambdaedge
Author: Vadim Reyder
Author-email: vadim.reyder@gmail.com
License: MIT
Platform: UNKNOWN
Requires-Dist: pulumi (<4.0.0,>=3.0.0)
Requires-Dist: pulumi-aws (<5.0.0,>=4.0.0)
